maoppy/__init__.py
maoppy/instrument.py
maoppy/psffit.py
maoppy/psfmodel.py
maoppy/psfutils.py
maoppy/utils.py
maoppy/zernike.py
maoppy/data/harmoni.ini
maoppy/data/muse_nfm.ini
maoppy/data/muse_wfm.ini
maoppy/data/papyrus.ini
maoppy/data/zimpol.ini
maoppy-1.6.1.dist-info/licenses/LICENSE
maoppy-1.6.1.dist-info/METADATA
maoppy-1.6.1.dist-info/WHEEL
maoppy-1.6.1.dist-info/top_level.txt
maoppy-1.6.1.dist-info/RECORD
