Metadata-Version: 2.4
Name: maoppy
Version: 1.6.1
Summary: Modelization of the Adaptive Optics Psf in PYthon
Author-email: Romain Fetick <romain.fetick@lam.fr>
License:                     GNU GENERAL PUBLIC LICENSE
Project-URL: repository, https://gitlab.lam.fr/lam-grd-public/maoppy
Keywords: PSF,AO,adaptive optics
Requires: numpy
Requires: scipy
Requires: astropy
Requires-Python: >=3.0
License-File: LICENSE
Requires-Dist: numpy
Requires-Dist: scipy
Requires-Dist: astropy
Dynamic: license-file
Dynamic: requires
